{
  "project_info": {
    "project_number": "487714998715",
    "project_id": "oms-ecom",
    "storage_bucket": "oms-ecom.firebasestorage.app"
  },
  "client": [
    {
      "client_info": {
        "mobilesdk_app_id": "1:487714998715:android:7b8d3d716fedf9f4141c9e",
        "android_client_info": {
          "package_name": "com.oms.ecommerce.omsecommerce"
        }
      },
      "oauth_client": [
        {
          "client_id": "487714998715-ou2pltjihcp7ci8e5402ug54nmt38rtl.apps.googleusercontent.com",
          "client_type": 1,
          "android_info": {
            "package_name": "com.oms.ecommerce.omsecommerce",
            "certificate_hash": "bcef607b68ae655536748c2c9be892d2fb36ba94"
          }
        },
        {
          "client_id": "487714998715-2f5e1fbrlkngea825u0eej84veth63po.apps.googleusercontent.com",
          "client_type": 3
        }
      ],
      "api_key": [
        {
          "current_key": "AIzaSyC1HkWdkRZbOV0d7JEY7k1XEjxjV3MvXu0"
        }
      ],
      "services": {
        "appinvite_service": {
          "other_platform_oauth_client": [
            {
              "client_id": "487714998715-2f5e1fbrlkngea825u0eej84veth63po.apps.googleusercontent.com",
              "client_type": 3
            },
            {
              "client_id": "487714998715-gbpmua9caetdlmf6i80k2isncp33glc6.apps.googleusercontent.com",
              "client_type": 2,
              "ios_info": {
                "bundle_id": "com.oms.ecommerce.omsecommerce"
              }
            }
          ]
        }
      }
    }
  ],
  "configuration_version": "1"
}